dragonfly_display/__init__.py
dragonfly_display/__main__.py
dragonfly_display/_extend_dragonfly.py
dragonfly_display/model.py
dragonfly_display/cli/__init__.py
dragonfly_display-0.3.10.dist-info/licenses/LICENSE
dragonfly_display-0.3.10.dist-info/METADATA
dragonfly_display-0.3.10.dist-info/WHEEL
dragonfly_display-0.3.10.dist-info/entry_points.txt
dragonfly_display-0.3.10.dist-info/top_level.txt
dragonfly_display-0.3.10.dist-info/RECORD
