Metadata-Version: 2.4
Name: dragonfly-display
Version: 0.3.10
Summary: Adds methods to translate dragonfly objects to VisualizationSets.
Home-page: https://github.com/ladybug-tools/dragonfly-display
Author: Ladybug Tools
Author-email: info@ladybug.tools
License: AGPL-3.0
Classifier: Programming Language :: Python :: 2.7
Classifier: Programming Language :: Python :: 3.7
Classifier: Programming Language :: Python :: 3.8
Classifier: Programming Language :: Python :: 3.9
Classifier: Programming Language :: Python :: 3.10
Classifier: Programming Language :: Python :: 3.11
Classifier: Programming Language :: Python :: 3.12
Classifier: Programming Language :: Python :: Implementation :: CPython
Classifier: Programming Language :: Python :: Implementation :: IronPython
Classifier: Operating System :: OS Independent
License-File: LICENSE
Requires-Dist: honeybee-display>=0.5.7
Requires-Dist: dragonfly-core>=1.73.0
Provides-Extra: full
Requires-Dist: dragonfly-energy>=1.25.28; extra == "full"
Requires-Dist: dragonfly-radiance>=0.3.20; extra == "full"
Requires-Dist: ladybug-vtk>=0.15.2; extra == "full"
Dynamic: author
Dynamic: author-email
Dynamic: classifier
Dynamic: description
Dynamic: description-content-type
Dynamic: home-page
Dynamic: license
Dynamic: license-file
Dynamic: provides-extra
Dynamic: requires-dist
Dynamic: summary
